pyslait/__init__.py
pyslait/client.py
pyslait/data.py
pyslait/stream.py
pyslait-0.1.dist-info/LICENSE
pyslait-0.1.dist-info/METADATA
pyslait-0.1.dist-info/WHEEL
pyslait-0.1.dist-info/top_level.txt
pyslait-0.1.dist-info/RECORD
