Metadata-Version: 2.1
Name: pyslait
Version: 0.1
Summary: Slait python driver
Home-page: https://github.com/xmurobi/pyslait
Author: robi
Author-email: xmurobi@gmail.com
License: UNKNOWN
Keywords: database,pandas,financial,timeseries
Platform: UNKNOWN
Requires-Dist: numpy
Requires-Dist: requests
Requires-Dist: pandas
Requires-Dist: six
Requires-Dist: urllib3
Requires-Dist: pytest
Requires-Dist: websocket-client
Requires-Dist: goto-statement
